repo_agent/__init__.py
repo_agent/__main__.py
repo_agent/change_detector.py
repo_agent/chat_engine.py
repo_agent/chat_with_repo/__init__.py
repo_agent/chat_with_repo/__main__.py
repo_agent/chat_with_repo/gradio_interface.py
repo_agent/chat_with_repo/json_handler.py
repo_agent/chat_with_repo/main.py
repo_agent/chat_with_repo/prompt.py
repo_agent/chat_with_repo/rag.py
repo_agent/chat_with_repo/text_analysis_tool.py
repo_agent/chat_with_repo/vector_store_manager.py
repo_agent/doc_meta_info.py
repo_agent/file_handler.py
repo_agent/log.py
repo_agent/main.py
repo_agent/multi_task_dispatch.py
repo_agent/project_manager.py
repo_agent/prompt.py
repo_agent/runner.py
repo_agent/settings.py
repo_agent/utils/gitignore_checker.py
repo_agent/utils/meta_info_utils.py
repoagent-0.2.0.dist-info/METADATA
repoagent-0.2.0.dist-info/WHEEL
repoagent-0.2.0.dist-info/entry_points.txt
repoagent-0.2.0.dist-info/licenses/LICENSE
repoagent-0.2.0.dist-info/RECORD
