Metadata-Version: 2.1
Name: repoagent
Version: 0.2.0
Summary: An LLM-Powered Framework for Repository-level Code Documentation Generation.
Author-Email: Qinyu Luo <qinyuluo123@gmail.com>
Maintainer-Email: Edwards Arno <Edwards.Arno@outlook.com>
License: Apache-2.0
Classifier: Programming Language :: Python :: 3
Classifier: Programming Language :: Python :: 3.11
Classifier: Programming Language :: Python :: 3.12
Classifier: Topic :: Scientific/Engineering :: Artificial Intelligence
Project-URL: repository, https://github.com/LOGIC-10/RepoAgent
Requires-Python: <4.0,>=3.11
Requires-Dist: loguru>=0.7.2
Requires-Dist: jedi>=0.19.1
Requires-Dist: GitPython>=3.1.41
Requires-Dist: prettytable>=3.9.0
Requires-Dist: python-iso639>=2024.2.7
Requires-Dist: pydantic-settings>=2.2.1
Requires-Dist: click>=8.1.7
Requires-Dist: python-iso639>=2024.10.22
Requires-Dist: colorama>=0.4.6
Requires-Dist: llama-index-llms-openai-like>=0.3.3
Provides-Extra: chat-with-repo
Requires-Dist: markdown>=3.7; extra == "chat-with-repo"
Requires-Dist: llama-index-embeddings-openai>=0.2.5; extra == "chat-with-repo"
Requires-Dist: llama-index-vector-stores-chroma>=0.3.0; extra == "chat-with-repo"
Requires-Dist: gradio>=5.6.0; extra == "chat-with-repo"
